aos_keys/__init__.py
aos_keys/__main__.py
aos_keys/actions.py
aos_keys/certificate_manager.py
aos_keys/check_version.py
aos_keys/cloud_api.py
aos_keys/common.py
aos_keys/crypto_container.py
aos_keys/key_manager.py
aos_keys/main.py
aos_keys/files/1rootCA.crt
aos_keys/files/__init__.py
aos_keys/files/aos_root_ca_1.crt
aos_keys/files/aos_root_ca_2.crt
aos_keys-1.9.0.dist-info/METADATA
aos_keys-1.9.0.dist-info/WHEEL
aos_keys-1.9.0.dist-info/entry_points.txt
aos_keys-1.9.0.dist-info/top_level.txt
aos_keys-1.9.0.dist-info/zip-safe
aos_keys-1.9.0.dist-info/RECORD
